pyproject.toml
torchsilk/__init__.py
torchsilk/distributions/__init__.py
torchsilk/distributions/base.py
torchsilk/distributions/normal.py
torchsilk/distributions/utils.py
torchsilk/init/__init__.py
torchsilk/init/core.py
torchsilk/init/orthogonal.py
torchsilk/init/type_defs.py
torchsilk/init/uniform.py
torchsilk/init/xavier.py
torchsilk/modules/__init__.py
torchsilk/modules/buffers.py
torchsilk/modules/functorch_.py
torchsilk/modules/module.py
torchsilk/modules/module_state.py
torchsilk/modules/train_state.py
torchsilk/modules/type_defs.py
torchsilk/py.typed
torchsilk/type_defs.py
torchsilk-0.7.0.dist-info/LICENSE
torchsilk-0.7.0.dist-info/WHEEL
torchsilk-0.7.0.dist-info/METADATA
torchsilk-0.7.0.dist-info/RECORD
